{
  "general": {
    "whois": "http://whois.domaintools.com/152.89.198.196",
    "reputation": 0,
    "indicator": "152.89.198.196",
    "type": "IPv4",
    "type_title": "IPv4",
    "base_indicator": {
      "id": 3731446062,
      "indicator": "152.89.198.196",
      "type": "IPv4",
      "title": "",
      "description": "",
      "content": "",
      "access_type": "public",
      "access_reason": ""
    },
    "pulse_info": {
      "count": 50,
      "pulses": [
        {
          "id": "666a51d286b205578ac80d48",
          "name": "Threat Listed",
          "description": "",
          "modified": "2025-02-01T06:05:35.310000",
          "created": "2024-06-13T01:56:34.275000",
          "tags": [],
          "references": [],
          "public": 1,
          "adversary": "",
          "targeted_countries": [],
          "malware_families": [],
          "attack_ids": [],
          "industries": [],
          "TLP": "green",
          "cloned_from": null,
          "export_count": 169,
          "upvotes_count": 0,
          "downvotes_count": 0,
          "votes_count": 0,
          "locked": false,
          "pulse_source": "web",
          "validator_count": 0,
          "comment_count": 0,
          "follower_count": 0,
          "vote": 0,
          "author": {
            "username": "edward21",
            "id": "279890",
            "avatar_url": "https://otx.alienvault.com/assets/images/default-avatar.png",
            "is_subscribed": false,
            "is_following": false
          },
          "indicator_type_counts": {},
          "indicator_count": 0,
          "is_author": false,
          "is_subscribing": null,
          "subscriber_count": 35,
          "modified_text": "63 days ago ",
          "is_modified": true,
          "groups": [],
          "in_group": false,
          "threat_hunter_scannable": false,
          "threat_hunter_has_agents": 1,
          "related_indicator_type": "IPv4",
          "related_indicator_is_active": 0,
          "targeted_technology": [],
          "organization": [],
          "targeted_botnet": [],
          "targeted_honeypot": [],
          "targeted_protocol": []
        },
        {
          "id": "6615d6998eba463f36adf923",
          "name": "hxxps://viz[.]greynoise[.]io/analysis/22fe6389-fe4a-49dc-b343-b6a2feb32864 - 04.04.24 by jwanihad (enriched)",
          "description": "",
          "modified": "2025-01-17T10:39:17.456000",
          "created": "2024-04-10T00:00:25.617000",
          "tags": [
            "virustotal"
          ],
          "references": [
            "https://www.virustotal.com/gui/collection/789999053bd7022e2d79a887a5f959be573ce57d6c4f3165503438fbd5dd9ad5/graph"
          ],
          "public": 1,
          "adversary": "",
          "targeted_countries": [],
          "malware_families": [],
          "attack_ids": [],
          "industries": [],
          "TLP": "white",
          "cloned_from": null,
          "export_count": 14,
          "upvotes_count": 0,
          "downvotes_count": 0,
          "votes_count": 0,
          "locked": false,
          "pulse_source": "web",
          "validator_count": 0,
          "comment_count": 1,
          "follower_count": 0,
          "vote": 0,
          "author": {
            "username": "skocherhan",
            "id": "249290",
            "avatar_url": "/otxapi/users/avatar_image/media/avatars/user_249290/resized/80/avatar_3b9c358f36.png",
            "is_subscribed": false,
            "is_following": false
          },
          "indicator_type_counts": {
            "URL": 2361,
            "domain": 632,
            "FileHash-SHA256": 644,
            "hostname": 918
          },
          "indicator_count": 4555,
          "is_author": false,
          "is_subscribing": null,
          "subscriber_count": 114,
          "modified_text": "78 days ago ",
          "is_modified": true,
          "groups": [],
          "in_group": false,
          "threat_hunter_scannable": true,
          "threat_hunter_has_agents": 1,
          "related_indicator_type": "IPv4",
          "related_indicator_is_active": 0,
          "targeted_technology": [],
          "organization": [
            "virustotal"
          ],
          "targeted_botnet": [],
          "targeted_honeypot": [],
          "targeted_protocol": []
        },
        {
          "id": "66c7e4a6bd2b7caaf151c09c",
          "name": "Compiled Blocklist of AbuseIPDB: Most reported IP addresses - by skocherhan",
          "description": "",
          "modified": "2024-08-23T01:23:50.830000",
          "created": "2024-08-23T01:23:50.830000",
          "tags": [
            "abuseipdb"
          ],
          "references": [
            "https://github.com/borestad/blocklist-abuseipdb/blob/main/abuseipdb-s100-3d.ipv4"
          ],
          "public": 1,
          "adversary": "",
          "targeted_countries": [],
          "malware_families": [],
          "attack_ids": [
            {
              "id": "T1046",
              "name": "Network Service Scanning",
              "display_name": "T1046 - Network Service Scanning"
            }
          ],
          "industries": [],
          "TLP": "white",
          "cloned_from": "668eff9bace226015f6c0184",
          "export_count": 12,
          "upvotes_count": 0,
          "downvotes_count": 0,
          "votes_count": 0,
          "locked": false,
          "pulse_source": "web",
          "validator_count": 0,
          "comment_count": 0,
          "follower_count": 0,
          "vote": 0,
          "author": {
            "username": "scoreblue",
            "id": "254100",
            "avatar_url": "/otxapi/users/avatar_image/media/avatars/user_254100/resized/80/avatar_3b9c358f36.png",
            "is_subscribed": false,
            "is_following": false
          },
          "indicator_type_counts": {
            "URL": 93
          },
          "indicator_count": 93,
          "is_author": false,
          "is_subscribing": null,
          "subscriber_count": 187,
          "modified_text": "225 days ago ",
          "is_modified": false,
          "groups": [],
          "in_group": false,
          "threat_hunter_scannable": false,
          "threat_hunter_has_agents": 1,
          "related_indicator_type": "IPv4",
          "related_indicator_is_active": 0,
          "targeted_technology": [],
          "organization": [
            "abuseipdb"
          ],
          "targeted_botnet": [],
          "targeted_honeypot": [],
          "targeted_protocol": []
        },
        {
          "id": "668eff9bace226015f6c0184",
          "name": "Aggregated Blocklist for AbuseIPDB: A list of the most reported IP addresses.",
          "description": "",
          "modified": "2024-08-09T21:00:13.835000",
          "created": "2024-07-10T21:39:39.479000",
          "tags": [
            "abuseipdb"
          ],
          "references": [
            "https://github.com/borestad/blocklist-abuseipdb/blob/main/abuseipdb-s100-3d.ipv4"
          ],
          "public": 1,
          "adversary": "",
          "targeted_countries": [],
          "malware_families": [],
          "attack_ids": [
            {
              "id": "T1046",
              "name": "Network Service Scanning",
              "display_name": "T1046 - Network Service Scanning"
            }
          ],
          "industries": [],
          "TLP": "white",
          "cloned_from": null,
          "export_count": 7,
          "upvotes_count": 0,
          "downvotes_count": 0,
          "votes_count": 0,
          "locked": false,
          "pulse_source": "web",
          "validator_count": 0,
          "comment_count": 0,
          "follower_count": 0,
          "vote": 0,
          "author": {
            "username": "skocherhan",
            "id": "249290",
            "avatar_url": "/otxapi/users/avatar_image/media/avatars/user_249290/resized/80/avatar_3b9c358f36.png",
            "is_subscribed": false,
            "is_following": false
          },
          "indicator_type_counts": {
            "URL": 93
          },
          "indicator_count": 93,
          "is_author": false,
          "is_subscribing": null,
          "subscriber_count": 112,
          "modified_text": "238 days ago ",
          "is_modified": true,
          "groups": [],
          "in_group": false,
          "threat_hunter_scannable": false,
          "threat_hunter_has_agents": 1,
          "related_indicator_type": "IPv4",
          "related_indicator_is_active": 0,
          "targeted_technology": [],
          "organization": [
            "abuseipdb"
          ],
          "targeted_botnet": [],
          "targeted_honeypot": [],
          "targeted_protocol": []
        },
        {
          "id": "668328c746d0c54293e139ee",
          "name": "Scan port 3389 RDP (S3#)",
          "description": "Scans hitting the server at TCP port 3389 RDP. Same IP should not appear more than once in 96 hours in our lists S3#.",
          "modified": "2024-07-31T22:04:27.566000",
          "created": "2024-07-01T22:08:07.658000",
          "tags": [
            "tcp",
            "RDP",
            "win",
            "windows",
            "admin",
            "honeypot",
            "Malicious IP",
            "botnet",
            "mirai",
            "blacklist",
            "scan"
          ],
          "references": [],
          "public": 1,
          "adversary": "",
          "targeted_countries": [],
          "malware_families": [],
          "attack_ids": [
            {
              "id": "T1595",
              "name": "",
              "display_name": ""
            }
          ],
          "industries": [],
          "TLP": "green",
          "cloned_from": null,
          "export_count": 8,
          "upvotes_count": 0,
          "downvotes_count": 0,
          "votes_count": 0,
          "locked": false,
          "pulse_source": "api",
          "validator_count": 0,
          "comment_count": 0,
          "follower_count": 0,
          "vote": 0,
          "author": {
            "username": "BotnetExposer",
            "id": "80256",
            "avatar_url": "/otxapi/users/avatar_image/media/avatars/user_80256/resized/80/avatar_f1760e796f.png",
            "is_subscribed": false,
            "is_following": false
          },
          "indicator_type_counts": {},
          "indicator_count": 0,
          "is_author": false,
          "is_subscribing": null,
          "subscriber_count": 2677,
          "modified_text": "247 days ago ",
          "is_modified": true,
          "groups": [],
          "in_group": false,
          "threat_hunter_scannable": false,
          "threat_hunter_has_agents": 1,
          "related_indicator_type": "IPv4",
          "related_indicator_is_active": 0,
          "targeted_technology": [
            "windows"
          ],
          "organization": [],
          "targeted_botnet": [
            "botnet",
            "mirai"
          ],
          "targeted_honeypot": [
            "honeypot"
          ],
          "targeted_protocol": [
            "tcp",
            "rdp"
          ]
        },
        {
          "id": "66983ef2d2e7185eac0d57df",
          "name": "ETIC Cybersecurity  2024-07-18  Port Scan",
          "description": "",
          "modified": "2024-07-18T19:49:34.492000",
          "created": "2024-07-17T22:00:18.853000",
          "tags": [],
          "references": [],
          "public": 1,
          "adversary": "",
          "targeted_countries": [],
          "malware_families": [],
          "attack_ids": [],
          "industries": [],
          "TLP": "white",
          "cloned_from": null,
          "export_count": 8,
          "upvotes_count": 0,
          "downvotes_count": 0,
          "votes_count": 0,
          "locked": false,
          "pulse_source": "api",
          "validator_count": 0,
          "comment_count": 0,
          "follower_count": 0,
          "vote": 0,
          "author": {
            "username": "EticCybersecurity",
            "id": "205841",
            "avatar_url": "/otxapi/users/avatar_image/media/avatars/user_205841/resized/80/avatar_3b9c358f36.png",
            "is_subscribed": false,
            "is_following": false
          },
          "indicator_type_counts": {},
          "indicator_count": 0,
          "is_author": false,
          "is_subscribing": null,
          "subscriber_count": 482,
          "modified_text": "260 days ago ",
          "is_modified": true,
          "groups": [],
          "in_group": false,
          "threat_hunter_scannable": false,
          "threat_hunter_has_agents": 1,
          "related_indicator_type": "IPv4",
          "related_indicator_is_active": 0,
          "targeted_technology": [],
          "organization": [],
          "targeted_botnet": [],
          "targeted_honeypot": [],
          "targeted_protocol": []
        },
        {
          "id": "6696ee2240f0326a34ca1713",
          "name": "ETIC Cybersecurity  2024-07-17  Port Scan",
          "description": "",
          "modified": "2024-07-17T22:00:06.539000",
          "created": "2024-07-16T22:03:14.988000",
          "tags": [],
          "references": [],
          "public": 1,
          "adversary": "",
          "targeted_countries": [],
          "malware_families": [],
          "attack_ids": [],
          "industries": [],
          "TLP": "white",
          "cloned_from": null,
          "export_count": 1,
          "upvotes_count": 0,
          "downvotes_count": 0,
          "votes_count": 0,
          "locked": false,
          "pulse_source": "api",
          "validator_count": 0,
          "comment_count": 0,
          "follower_count": 0,
          "vote": 0,
          "author": {
            "username": "EticCybersecurity",
            "id": "205841",
            "avatar_url": "/otxapi/users/avatar_image/media/avatars/user_205841/resized/80/avatar_3b9c358f36.png",
            "is_subscribed": false,
            "is_following": false
          },
          "indicator_type_counts": {},
          "indicator_count": 0,
          "is_author": false,
          "is_subscribing": null,
          "subscriber_count": 481,
          "modified_text": "261 days ago ",
          "is_modified": true,
          "groups": [],
          "in_group": false,
          "threat_hunter_scannable": false,
          "threat_hunter_has_agents": 1,
          "related_indicator_type": "IPv4",
          "related_indicator_is_active": 0,
          "targeted_technology": [],
          "organization": [],
          "targeted_botnet": [],
          "targeted_honeypot": [],
          "targeted_protocol": []
        },
        {
          "id": "66959bff77c623a90bf012af",
          "name": "ETIC Cybersecurity  2024-07-16  Port Scan",
          "description": "",
          "modified": "2024-07-16T22:03:03.669000",
          "created": "2024-07-15T22:00:31.622000",
          "tags": [],
          "references": [],
          "public": 1,
          "adversary": "",
          "targeted_countries": [],
          "malware_families": [],
          "attack_ids": [],
          "industries": [],
          "TLP": "white",
          "cloned_from": null,
          "export_count": 1,
          "upvotes_count": 0,
          "downvotes_count": 0,
          "votes_count": 0,
          "locked": false,
          "pulse_source": "api",
          "validator_count": 0,
          "comment_count": 0,
          "follower_count": 0,
          "vote": 0,
          "author": {
            "username": "EticCybersecurity",
            "id": "205841",
            "avatar_url": "/otxapi/users/avatar_image/media/avatars/user_205841/resized/80/avatar_3b9c358f36.png",
            "is_subscribed": false,
            "is_following": false
          },
          "indicator_type_counts": {},
          "indicator_count": 0,
          "is_author": false,
          "is_subscribing": null,
          "subscriber_count": 481,
          "modified_text": "262 days ago ",
          "is_modified": true,
          "groups": [],
          "in_group": false,
          "threat_hunter_scannable": false,
          "threat_hunter_has_agents": 1,
          "related_indicator_type": "IPv4",
          "related_indicator_is_active": 0,
          "targeted_technology": [],
          "organization": [],
          "targeted_botnet": [],
          "targeted_honeypot": [],
          "targeted_protocol": []
        },
        {
          "id": "66944a7285a4f65f5a046c33",
          "name": "ETIC Cybersecurity  2024-07-15  Port Scan",
          "description": "",
          "modified": "2024-07-15T22:00:21.001000",
          "created": "2024-07-14T22:00:18.888000",
          "tags": [],
          "references": [],
          "public": 1,
          "adversary": "",
          "targeted_countries": [],
          "malware_families": [],
          "attack_ids": [],
          "industries": [],
          "TLP": "white",
          "cloned_from": null,
          "export_count": 1,
          "upvotes_count": 0,
          "downvotes_count": 0,
          "votes_count": 0,
          "locked": false,
          "pulse_source": "api",
          "validator_count": 0,
          "comment_count": 0,
          "follower_count": 0,
          "vote": 0,
          "author": {
            "username": "EticCybersecurity",
            "id": "205841",
            "avatar_url": "/otxapi/users/avatar_image/media/avatars/user_205841/resized/80/avatar_3b9c358f36.png",
            "is_subscribed": false,
            "is_following": false
          },
          "indicator_type_counts": {},
          "indicator_count": 0,
          "is_author": false,
          "is_subscribing": null,
          "subscriber_count": 479,
          "modified_text": "263 days ago ",
          "is_modified": true,
          "groups": [],
          "in_group": false,
          "threat_hunter_scannable": false,
          "threat_hunter_has_agents": 1,
          "related_indicator_type": "IPv4",
          "related_indicator_is_active": 0,
          "targeted_technology": [],
          "organization": [],
          "targeted_botnet": [],
          "targeted_honeypot": [],
          "targeted_protocol": []
        },
        {
          "id": "6692f90b2fe621da12c66a1d",
          "name": "ETIC Cybersecurity  2024-07-14  Port Scan",
          "description": "",
          "modified": "2024-07-14T22:00:07.738000",
          "created": "2024-07-13T22:00:42.058000",
          "tags": [],
          "references": [],
          "public": 1,
          "adversary": "",
          "targeted_countries": [],
          "malware_families": [],
          "attack_ids": [],
          "industries": [],
          "TLP": "white",
          "cloned_from": null,
          "export_count": 2,
          "upvotes_count": 0,
          "downvotes_count": 0,
          "votes_count": 0,
          "locked": false,
          "pulse_source": "api",
          "validator_count": 0,
          "comment_count": 0,
          "follower_count": 0,
          "vote": 0,
          "author": {
            "username": "EticCybersecurity",
            "id": "205841",
            "avatar_url": "/otxapi/users/avatar_image/media/avatars/user_205841/resized/80/avatar_3b9c358f36.png",
            "is_subscribed": false,
            "is_following": false
          },
          "indicator_type_counts": {},
          "indicator_count": 0,
          "is_author": false,
          "is_subscribing": null,
          "subscriber_count": 476,
          "modified_text": "264 days ago ",
          "is_modified": true,
          "groups": [],
          "in_group": false,
          "threat_hunter_scannable": false,
          "threat_hunter_has_agents": 1,
          "related_indicator_type": "IPv4",
          "related_indicator_is_active": 0,
          "targeted_technology": [],
          "organization": [],
          "targeted_botnet": [],
          "targeted_honeypot": [],
          "targeted_protocol": []
        },
        {
          "id": "6691a7a8d302927c7483d5c2",
          "name": "ETIC Cybersecurity  2024-07-13  Port Scan",
          "description": "",
          "modified": "2024-07-13T22:00:23.286000",
          "created": "2024-07-12T22:01:12.182000",
          "tags": [],
          "references": [],
          "public": 1,
          "adversary": "",
          "targeted_countries": [],
          "malware_families": [],
          "attack_ids": [],
          "industries": [],
          "TLP": "white",
          "cloned_from": null,
          "export_count": 3,
          "upvotes_count": 0,
          "downvotes_count": 0,
          "votes_count": 0,
          "locked": false,
          "pulse_source": "api",
          "validator_count": 0,
          "comment_count": 0,
          "follower_count": 0,
          "vote": 0,
          "author": {
            "username": "EticCybersecurity",
            "id": "205841",
            "avatar_url": "/otxapi/users/avatar_image/media/avatars/user_205841/resized/80/avatar_3b9c358f36.png",
            "is_subscribed": false,
            "is_following": false
          },
          "indicator_type_counts": {},
          "indicator_count": 0,
          "is_author": false,
          "is_subscribing": null,
          "subscriber_count": 478,
          "modified_text": "265 days ago ",
          "is_modified": true,
          "groups": [],
          "in_group": false,
          "threat_hunter_scannable": false,
          "threat_hunter_has_agents": 1,
          "related_indicator_type": "IPv4",
          "related_indicator_is_active": 0,
          "targeted_technology": [],
          "organization": [],
          "targeted_botnet": [],
          "targeted_honeypot": [],
          "targeted_protocol": []
        },
        {
          "id": "66905612141d47ecaec3b200",
          "name": "ETIC Cybersecurity  2024-07-12  Port Scan",
          "description": "",
          "modified": "2024-07-12T22:00:52.500000",
          "created": "2024-07-11T22:00:50.948000",
          "tags": [],
          "references": [],
          "public": 1,
          "adversary": "",
          "targeted_countries": [],
          "malware_families": [],
          "attack_ids": [],
          "industries": [],
          "TLP": "white",
          "cloned_from": null,
          "export_count": 0,
          "upvotes_count": 0,
          "downvotes_count": 0,
          "votes_count": 0,
          "locked": false,
          "pulse_source": "api",
          "validator_count": 0,
          "comment_count": 0,
          "follower_count": 0,
          "vote": 0,
          "author": {
            "username": "EticCybersecurity",
            "id": "205841",
            "avatar_url": "/otxapi/users/avatar_image/media/avatars/user_205841/resized/80/avatar_3b9c358f36.png",
            "is_subscribed": false,
            "is_following": false
          },
          "indicator_type_counts": {},
          "indicator_count": 0,
          "is_author": false,
          "is_subscribing": null,
          "subscriber_count": 477,
          "modified_text": "266 days ago ",
          "is_modified": true,
          "groups": [],
          "in_group": false,
          "threat_hunter_scannable": false,
          "threat_hunter_has_agents": 1,
          "related_indicator_type": "IPv4",
          "related_indicator_is_active": 0,
          "targeted_technology": [],
          "organization": [],
          "targeted_botnet": [],
          "targeted_honeypot": [],
          "targeted_protocol": []
        },
        {
          "id": "668f046dee26b4beff9c27e8",
          "name": "ETIC Cybersecurity  2024-07-11  Port Scan",
          "description": "",
          "modified": "2024-07-11T22:00:06.616000",
          "created": "2024-07-10T22:00:13.375000",
          "tags": [],
          "references": [],
          "public": 1,
          "adversary": "",
          "targeted_countries": [],
          "malware_families": [],
          "attack_ids": [],
          "industries": [],
          "TLP": "white",
          "cloned_from": null,
          "export_count": 1,
          "upvotes_count": 0,
          "downvotes_count": 0,
          "votes_count": 0,
          "locked": false,
          "pulse_source": "api",
          "validator_count": 0,
          "comment_count": 0,
          "follower_count": 0,
          "vote": 0,
          "author": {
            "username": "EticCybersecurity",
            "id": "205841",
            "avatar_url": "/otxapi/users/avatar_image/media/avatars/user_205841/resized/80/avatar_3b9c358f36.png",
            "is_subscribed": false,
            "is_following": false
          },
          "indicator_type_counts": {},
          "indicator_count": 0,
          "is_author": false,
          "is_subscribing": null,
          "subscriber_count": 481,
          "modified_text": "267 days ago ",
          "is_modified": true,
          "groups": [],
          "in_group": false,
          "threat_hunter_scannable": false,
          "threat_hunter_has_agents": 1,
          "related_indicator_type": "IPv4",
          "related_indicator_is_active": 0,
          "targeted_technology": [],
          "organization": [],
          "targeted_botnet": [],
          "targeted_honeypot": [],
          "targeted_protocol": []
        },
        {
          "id": "668db3169e78051f357151b1",
          "name": "ETIC Cybersecurity  2024-07-10  Port Scan",
          "description": "",
          "modified": "2024-07-10T21:59:47.986000",
          "created": "2024-07-09T22:00:54.889000",
          "tags": [],
          "references": [],
          "public": 1,
          "adversary": "",
          "targeted_countries": [],
          "malware_families": [],
          "attack_ids": [],
          "industries": [],
          "TLP": "white",
          "cloned_from": null,
          "export_count": 8,
          "upvotes_count": 0,
          "downvotes_count": 0,
          "votes_count": 0,
          "locked": false,
          "pulse_source": "api",
          "validator_count": 0,
          "comment_count": 0,
          "follower_count": 0,
          "vote": 0,
          "author": {
            "username": "EticCybersecurity",
            "id": "205841",
            "avatar_url": "/otxapi/users/avatar_image/media/avatars/user_205841/resized/80/avatar_3b9c358f36.png",
            "is_subscribed": false,
            "is_following": false
          },
          "indicator_type_counts": {},
          "indicator_count": 0,
          "is_author": false,
          "is_subscribing": null,
          "subscriber_count": 484,
          "modified_text": "268 days ago ",
          "is_modified": true,
          "groups": [],
          "in_group": false,
          "threat_hunter_scannable": false,
          "threat_hunter_has_agents": 1,
          "related_indicator_type": "IPv4",
          "related_indicator_is_active": 0,
          "targeted_technology": [],
          "organization": [],
          "targeted_botnet": [],
          "targeted_honeypot": [],
          "targeted_protocol": []
        },
        {
          "id": "668c618364488ac4f0e785af",
          "name": "ETIC Cybersecurity  2024-07-09  Port Scan",
          "description": "",
          "modified": "2024-07-09T22:00:09.625000",
          "created": "2024-07-08T22:00:35.279000",
          "tags": [],
          "references": [],
          "public": 1,
          "adversary": "",
          "targeted_countries": [],
          "malware_families": [],
          "attack_ids": [],
          "industries": [],
          "TLP": "white",
          "cloned_from": null,
          "export_count": 3,
          "upvotes_count": 0,
          "downvotes_count": 0,
          "votes_count": 0,
          "locked": false,
          "pulse_source": "api",
          "validator_count": 0,
          "comment_count": 0,
          "follower_count": 0,
          "vote": 0,
          "author": {
            "username": "EticCybersecurity",
            "id": "205841",
            "avatar_url": "/otxapi/users/avatar_image/media/avatars/user_205841/resized/80/avatar_3b9c358f36.png",
            "is_subscribed": false,
            "is_following": false
          },
          "indicator_type_counts": {},
          "indicator_count": 0,
          "is_author": false,
          "is_subscribing": null,
          "subscriber_count": 478,
          "modified_text": "269 days ago ",
          "is_modified": true,
          "groups": [],
          "in_group": false,
          "threat_hunter_scannable": false,
          "threat_hunter_has_agents": 1,
          "related_indicator_type": "IPv4",
          "related_indicator_is_active": 0,
          "targeted_technology": [],
          "organization": [],
          "targeted_botnet": [],
          "targeted_honeypot": [],
          "targeted_protocol": []
        },
        {
          "id": "668b100039a5a0977c397594",
          "name": "ETIC Cybersecurity  2024-07-08  Port Scan",
          "description": "",
          "modified": "2024-07-08T22:00:15.108000",
          "created": "2024-07-07T22:00:32.613000",
          "tags": [],
          "references": [],
          "public": 1,
          "adversary": "",
          "targeted_countries": [],
          "malware_families": [],
          "attack_ids": [],
          "industries": [],
          "TLP": "white",
          "cloned_from": null,
          "export_count": 6,
          "upvotes_count": 0,
          "downvotes_count": 0,
          "votes_count": 0,
          "locked": false,
          "pulse_source": "api",
          "validator_count": 0,
          "comment_count": 0,
          "follower_count": 0,
          "vote": 0,
          "author": {
            "username": "EticCybersecurity",
            "id": "205841",
            "avatar_url": "/otxapi/users/avatar_image/media/avatars/user_205841/resized/80/avatar_3b9c358f36.png",
            "is_subscribed": false,
            "is_following": false
          },
          "indicator_type_counts": {},
          "indicator_count": 0,
          "is_author": false,
          "is_subscribing": null,
          "subscriber_count": 480,
          "modified_text": "270 days ago ",
          "is_modified": true,
          "groups": [],
          "in_group": false,
          "threat_hunter_scannable": false,
          "threat_hunter_has_agents": 1,
          "related_indicator_type": "IPv4",
          "related_indicator_is_active": 0,
          "targeted_technology": [],
          "organization": [],
          "targeted_botnet": [],
          "targeted_honeypot": [],
          "targeted_protocol": []
        },
        {
          "id": "6689be8c3777742fea290852",
          "name": "ETIC Cybersecurity  2024-07-07  Port Scan",
          "description": "",
          "modified": "2024-07-07T22:00:17.572000",
          "created": "2024-07-06T22:00:44.001000",
          "tags": [],
          "references": [],
          "public": 1,
          "adversary": "",
          "targeted_countries": [],
          "malware_families": [],
          "attack_ids": [],
          "industries": [],
          "TLP": "white",
          "cloned_from": null,
          "export_count": 2,
          "upvotes_count": 0,
          "downvotes_count": 0,
          "votes_count": 0,
          "locked": false,
          "pulse_source": "api",
          "validator_count": 0,
          "comment_count": 0,
          "follower_count": 0,
          "vote": 0,
          "author": {
            "username": "EticCybersecurity",
            "id": "205841",
            "avatar_url": "/otxapi/users/avatar_image/media/avatars/user_205841/resized/80/avatar_3b9c358f36.png",
            "is_subscribed": false,
            "is_following": false
          },
          "indicator_type_counts": {},
          "indicator_count": 0,
          "is_author": false,
          "is_subscribing": null,
          "subscriber_count": 477,
          "modified_text": "271 days ago ",
          "is_modified": true,
          "groups": [],
          "in_group": false,
          "threat_hunter_scannable": false,
          "threat_hunter_has_agents": 1,
          "related_indicator_type": "IPv4",
          "related_indicator_is_active": 0,
          "targeted_technology": [],
          "organization": [],
          "targeted_botnet": [],
          "targeted_honeypot": [],
          "targeted_protocol": []
        },
        {
          "id": "66886d111b8906e5b7ae8c3f",
          "name": "ETIC Cybersecurity  2024-07-06  Port Scan",
          "description": "",
          "modified": "2024-07-06T21:59:49.279000",
          "created": "2024-07-05T22:00:49.284000",
          "tags": [],
          "references": [],
          "public": 1,
          "adversary": "",
          "targeted_countries": [],
          "malware_families": [],
          "attack_ids": [],
          "industries": [],
          "TLP": "white",
          "cloned_from": null,
          "export_count": 4,
          "upvotes_count": 0,
          "downvotes_count": 0,
          "votes_count": 0,
          "locked": false,
          "pulse_source": "api",
          "validator_count": 0,
          "comment_count": 0,
          "follower_count": 0,
          "vote": 0,
          "author": {
            "username": "EticCybersecurity",
            "id": "205841",
            "avatar_url": "/otxapi/users/avatar_image/media/avatars/user_205841/resized/80/avatar_3b9c358f36.png",
            "is_subscribed": false,
            "is_following": false
          },
          "indicator_type_counts": {},
          "indicator_count": 0,
          "is_author": false,
          "is_subscribing": null,
          "subscriber_count": 476,
          "modified_text": "272 days ago ",
          "is_modified": true,
          "groups": [],
          "in_group": false,
          "threat_hunter_scannable": false,
          "threat_hunter_has_agents": 1,
          "related_indicator_type": "IPv4",
          "related_indicator_is_active": 0,
          "targeted_technology": [],
          "organization": [],
          "targeted_botnet": [],
          "targeted_honeypot": [],
          "targeted_protocol": []
        },
        {
          "id": "6660e1ad1922ad038f1594b2",
          "name": "Scan port 3389 RDP (S3#)",
          "description": "Scans hitting the server at TCP port 3389 RDP. Same IP should not appear more than once in 96 hours in our lists S3#.",
          "modified": "2024-07-05T22:03:16.686000",
          "created": "2024-06-05T22:07:40.956000",
          "tags": [
            "tcp",
            "RDP",
            "win",
            "windows",
            "admin",
            "honeypot",
            "Malicious IP",
            "botnet",
            "mirai",
            "blacklist",
            "scan"
          ],
          "references": [],
          "public": 1,
          "adversary": "",
          "targeted_countries": [],
          "malware_families": [],
          "attack_ids": [
            {
              "id": "T1595",
              "name": "",
              "display_name": ""
            }
          ],
          "industries": [],
          "TLP": "green",
          "cloned_from": null,
          "export_count": 18,
          "upvotes_count": 0,
          "downvotes_count": 0,
          "votes_count": 0,
          "locked": false,
          "pulse_source": "api",
          "validator_count": 0,
          "comment_count": 0,
          "follower_count": 0,
          "vote": 0,
          "author": {
            "username": "BotnetExposer",
            "id": "80256",
            "avatar_url": "/otxapi/users/avatar_image/media/avatars/user_80256/resized/80/avatar_f1760e796f.png",
            "is_subscribed": false,
            "is_following": false
          },
          "indicator_type_counts": {},
          "indicator_count": 0,
          "is_author": false,
          "is_subscribing": null,
          "subscriber_count": 2677,
          "modified_text": "273 days ago ",
          "is_modified": true,
          "groups": [],
          "in_group": false,
          "threat_hunter_scannable": false,
          "threat_hunter_has_agents": 1,
          "related_indicator_type": "IPv4",
          "related_indicator_is_active": 0,
          "targeted_technology": [
            "windows"
          ],
          "organization": [],
          "targeted_botnet": [
            "botnet",
            "mirai"
          ],
          "targeted_honeypot": [
            "honeypot"
          ],
          "targeted_protocol": [
            "tcp",
            "rdp"
          ]
        },
        {
          "id": "66871b847e503e9b15aef17e",
          "name": "ETIC Cybersecurity  2024-07-05  Port Scan",
          "description": "",
          "modified": "2024-07-05T22:00:00.807000",
          "created": "2024-07-04T22:00:36.872000",
          "tags": [],
          "references": [],
          "public": 1,
          "adversary": "",
          "targeted_countries": [],
          "malware_families": [],
          "attack_ids": [],
          "industries": [],
          "TLP": "white",
          "cloned_from": null,
          "export_count": 4,
          "upvotes_count": 0,
          "downvotes_count": 0,
          "votes_count": 0,
          "locked": false,
          "pulse_source": "api",
          "validator_count": 0,
          "comment_count": 0,
          "follower_count": 0,
          "vote": 0,
          "author": {
            "username": "EticCybersecurity",
            "id": "205841",
            "avatar_url": "/otxapi/users/avatar_image/media/avatars/user_205841/resized/80/avatar_3b9c358f36.png",
            "is_subscribed": false,
            "is_following": false
          },
          "indicator_type_counts": {},
          "indicator_count": 0,
          "is_author": false,
          "is_subscribing": null,
          "subscriber_count": 479,
          "modified_text": "273 days ago ",
          "is_modified": true,
          "groups": [],
          "in_group": false,
          "threat_hunter_scannable": false,
          "threat_hunter_has_agents": 1,
          "related_indicator_type": "IPv4",
          "related_indicator_is_active": 0,
          "targeted_technology": [],
          "organization": [],
          "targeted_botnet": [],
          "targeted_honeypot": [],
          "targeted_protocol": []
        },
        {
          "id": "6685c9fb04cbcd1b5cdd0c21",
          "name": "ETIC Cybersecurity  2024-07-04  Port Scan",
          "description": "",
          "modified": "2024-07-04T21:59:52.728000",
          "created": "2024-07-03T22:00:27.206000",
          "tags": [],
          "references": [],
          "public": 1,
          "adversary": "",
          "targeted_countries": [],
          "malware_families": [],
          "attack_ids": [],
          "industries": [],
          "TLP": "white",
          "cloned_from": null,
          "export_count": 5,
          "upvotes_count": 0,
          "downvotes_count": 0,
          "votes_count": 0,
          "locked": false,
          "pulse_source": "api",
          "validator_count": 0,
          "comment_count": 0,
          "follower_count": 0,
          "vote": 0,
          "author": {
            "username": "EticCybersecurity",
            "id": "205841",
            "avatar_url": "/otxapi/users/avatar_image/media/avatars/user_205841/resized/80/avatar_3b9c358f36.png",
            "is_subscribed": false,
            "is_following": false
          },
          "indicator_type_counts": {},
          "indicator_count": 0,
          "is_author": false,
          "is_subscribing": null,
          "subscriber_count": 478,
          "modified_text": "274 days ago ",
          "is_modified": true,
          "groups": [],
          "in_group": false,
          "threat_hunter_scannable": false,
          "threat_hunter_has_agents": 1,
          "related_indicator_type": "IPv4",
          "related_indicator_is_active": 0,
          "targeted_technology": [],
          "organization": [],
          "targeted_botnet": [],
          "targeted_honeypot": [],
          "targeted_protocol": []
        },
        {
          "id": "6684787f66ca3db138d2824c",
          "name": "ETIC Cybersecurity  2024-07-03  Port Scan",
          "description": "",
          "modified": "2024-07-03T21:59:55.391000",
          "created": "2024-07-02T22:00:31.045000",
          "tags": [],
          "references": [],
          "public": 1,
          "adversary": "",
          "targeted_countries": [],
          "malware_families": [],
          "attack_ids": [],
          "industries": [],
          "TLP": "white",
          "cloned_from": null,
          "export_count": 2,
          "upvotes_count": 0,
          "downvotes_count": 0,
          "votes_count": 0,
          "locked": false,
          "pulse_source": "api",
          "validator_count": 0,
          "comment_count": 0,
          "follower_count": 0,
          "vote": 0,
          "author": {
            "username": "EticCybersecurity",
            "id": "205841",
            "avatar_url": "/otxapi/users/avatar_image/media/avatars/user_205841/resized/80/avatar_3b9c358f36.png",
            "is_subscribed": false,
            "is_following": false
          },
          "indicator_type_counts": {},
          "indicator_count": 0,
          "is_author": false,
          "is_subscribing": null,
          "subscriber_count": 483,
          "modified_text": "275 days ago ",
          "is_modified": true,
          "groups": [],
          "in_group": false,
          "threat_hunter_scannable": false,
          "threat_hunter_has_agents": 1,
          "related_indicator_type": "IPv4",
          "related_indicator_is_active": 0,
          "targeted_technology": [],
          "organization": [],
          "targeted_botnet": [],
          "targeted_honeypot": [],
          "targeted_protocol": []
        },
        {
          "id": "66834fa0eaa6631a15708fee",
          "name": "ETIC Cybersecurity  2024-07-02  Port Scan",
          "description": "",
          "modified": "2024-07-02T21:59:51.123000",
          "created": "2024-07-02T00:53:52.114000",
          "tags": [],
          "references": [],
          "public": 1,
          "adversary": "",
          "targeted_countries": [],
          "malware_families": [],
          "attack_ids": [],
          "industries": [],
          "TLP": "white",
          "cloned_from": null,
          "export_count": 5,
          "upvotes_count": 0,
          "downvotes_count": 0,
          "votes_count": 0,
          "locked": false,
          "pulse_source": "api",
          "validator_count": 0,
          "comment_count": 0,
          "follower_count": 0,
          "vote": 0,
          "author": {
            "username": "EticCybersecurity",
            "id": "205841",
            "avatar_url": "/otxapi/users/avatar_image/media/avatars/user_205841/resized/80/avatar_3b9c358f36.png",
            "is_subscribed": false,
            "is_following": false
          },
          "indicator_type_counts": {},
          "indicator_count": 0,
          "is_author": false,
          "is_subscribing": null,
          "subscriber_count": 480,
          "modified_text": "276 days ago ",
          "is_modified": true,
          "groups": [],
          "in_group": false,
          "threat_hunter_scannable": false,
          "threat_hunter_has_agents": 1,
          "related_indicator_type": "IPv4",
          "related_indicator_is_active": 0,
          "targeted_technology": [],
          "organization": [],
          "targeted_botnet": [],
          "targeted_honeypot": [],
          "targeted_protocol": []
        },
        {
          "id": "6681d572d756385e7cce481e",
          "name": "ETIC Cybersecurity  2024-07-01  Port Scan",
          "description": "",
          "modified": "2024-07-02T00:53:23.588000",
          "created": "2024-06-30T22:00:18.887000",
          "tags": [],
          "references": [],
          "public": 1,
          "adversary": "",
          "targeted_countries": [],
          "malware_families": [],
          "attack_ids": [],
          "industries": [],
          "TLP": "white",
          "cloned_from": null,
          "export_count": 4,
          "upvotes_count": 0,
          "downvotes_count": 0,
          "votes_count": 0,
          "locked": false,
          "pulse_source": "api",
          "validator_count": 0,
          "comment_count": 0,
          "follower_count": 0,
          "vote": 0,
          "author": {
            "username": "EticCybersecurity",
            "id": "205841",
            "avatar_url": "/otxapi/users/avatar_image/media/avatars/user_205841/resized/80/avatar_3b9c358f36.png",
            "is_subscribed": false,
            "is_following": false
          },
          "indicator_type_counts": {},
          "indicator_count": 0,
          "is_author": false,
          "is_subscribing": null,
          "subscriber_count": 478,
          "modified_text": "277 days ago ",
          "is_modified": true,
          "groups": [],
          "in_group": false,
          "threat_hunter_scannable": false,
          "threat_hunter_has_agents": 1,
          "related_indicator_type": "IPv4",
          "related_indicator_is_active": 0,
          "targeted_technology": [],
          "organization": [],
          "targeted_botnet": [],
          "targeted_honeypot": [],
          "targeted_protocol": []
        },
        {
          "id": "6679ec6304ceee4f99bcfc17",
          "name": "ETIC Cybersecurity  2024-06-25  Port Scan",
          "description": "",
          "modified": "2024-06-25T22:00:00.994000",
          "created": "2024-06-24T22:00:03.886000",
          "tags": [],
          "references": [],
          "public": 1,
          "adversary": "",
          "targeted_countries": [],
          "malware_families": [],
          "attack_ids": [],
          "industries": [],
          "TLP": "white",
          "cloned_from": null,
          "export_count": 4,
          "upvotes_count": 0,
          "downvotes_count": 0,
          "votes_count": 0,
          "locked": false,
          "pulse_source": "api",
          "validator_count": 0,
          "comment_count": 0,
          "follower_count": 0,
          "vote": 0,
          "author": {
            "username": "EticCybersecurity",
            "id": "205841",
            "avatar_url": "/otxapi/users/avatar_image/media/avatars/user_205841/resized/80/avatar_3b9c358f36.png",
            "is_subscribed": false,
            "is_following": false
          },
          "indicator_type_counts": {},
          "indicator_count": 0,
          "is_author": false,
          "is_subscribing": null,
          "subscriber_count": 480,
          "modified_text": "283 days ago ",
          "is_modified": true,
          "groups": [],
          "in_group": false,
          "threat_hunter_scannable": false,
          "threat_hunter_has_agents": 1,
          "related_indicator_type": "IPv4",
          "related_indicator_is_active": 0,
          "targeted_technology": [],
          "organization": [],
          "targeted_botnet": [],
          "targeted_honeypot": [],
          "targeted_protocol": []
        },
        {
          "id": "66789ae7f2e7199770c756b2",
          "name": "ETIC Cybersecurity  2024-06-24  Port Scan",
          "description": "",
          "modified": "2024-06-24T21:59:51.021000",
          "created": "2024-06-23T22:00:07.053000",
          "tags": [],
          "references": [],
          "public": 1,
          "adversary": "",
          "targeted_countries": [],
          "malware_families": [],
          "attack_ids": [],
          "industries": [],
          "TLP": "white",
          "cloned_from": null,
          "export_count": 6,
          "upvotes_count": 0,
          "downvotes_count": 0,
          "votes_count": 0,
          "locked": false,
          "pulse_source": "api",
          "validator_count": 0,
          "comment_count": 0,
          "follower_count": 0,
          "vote": 0,
          "author": {
            "username": "EticCybersecurity",
            "id": "205841",
            "avatar_url": "/otxapi/users/avatar_image/media/avatars/user_205841/resized/80/avatar_3b9c358f36.png",
            "is_subscribed": false,
            "is_following": false
          },
          "indicator_type_counts": {},
          "indicator_count": 0,
          "is_author": false,
          "is_subscribing": null,
          "subscriber_count": 477,
          "modified_text": "284 days ago ",
          "is_modified": true,
          "groups": [],
          "in_group": false,
          "threat_hunter_scannable": false,
          "threat_hunter_has_agents": 1,
          "related_indicator_type": "IPv4",
          "related_indicator_is_active": 0,
          "targeted_technology": [],
          "organization": [],
          "targeted_botnet": [],
          "targeted_honeypot": [],
          "targeted_protocol": []
        },
        {
          "id": "667749760e7b8240407eb9c9",
          "name": "ETIC Cybersecurity  2024-06-23  Port Scan",
          "description": "",
          "modified": "2024-06-23T21:59:54.069000",
          "created": "2024-06-22T22:00:22.600000",
          "tags": [],
          "references": [],
          "public": 1,
          "adversary": "",
          "targeted_countries": [],
          "malware_families": [],
          "attack_ids": [],
          "industries": [],
          "TLP": "white",
          "cloned_from": null,
          "export_count": 1,
          "upvotes_count": 0,
          "downvotes_count": 0,
          "votes_count": 0,
          "locked": false,
          "pulse_source": "api",
          "validator_count": 0,
          "comment_count": 0,
          "follower_count": 0,
          "vote": 0,
          "author": {
            "username": "EticCybersecurity",
            "id": "205841",
            "avatar_url": "/otxapi/users/avatar_image/media/avatars/user_205841/resized/80/avatar_3b9c358f36.png",
            "is_subscribed": false,
            "is_following": false
          },
          "indicator_type_counts": {},
          "indicator_count": 0,
          "is_author": false,
          "is_subscribing": null,
          "subscriber_count": 479,
          "modified_text": "285 days ago ",
          "is_modified": true,
          "groups": [],
          "in_group": false,
          "threat_hunter_scannable": false,
          "threat_hunter_has_agents": 1,
          "related_indicator_type": "IPv4",
          "related_indicator_is_active": 0,
          "targeted_technology": [],
          "organization": [],
          "targeted_botnet": [],
          "targeted_honeypot": [],
          "targeted_protocol": []
        },
        {
          "id": "6675f7e775a670df0fc458e7",
          "name": "ETIC Cybersecurity  2024-06-22  Port Scan",
          "description": "",
          "modified": "2024-06-22T22:00:08.366000",
          "created": "2024-06-21T22:00:06.779000",
          "tags": [],
          "references": [],
          "public": 1,
          "adversary": "",
          "targeted_countries": [],
          "malware_families": [],
          "attack_ids": [],
          "industries": [],
          "TLP": "white",
          "cloned_from": null,
          "export_count": 14,
          "upvotes_count": 0,
          "downvotes_count": 0,
          "votes_count": 0,
          "locked": false,
          "pulse_source": "api",
          "validator_count": 0,
          "comment_count": 0,
          "follower_count": 0,
          "vote": 0,
          "author": {
            "username": "EticCybersecurity",
            "id": "205841",
            "avatar_url": "/otxapi/users/avatar_image/media/avatars/user_205841/resized/80/avatar_3b9c358f36.png",
            "is_subscribed": false,
            "is_following": false
          },
          "indicator_type_counts": {},
          "indicator_count": 0,
          "is_author": false,
          "is_subscribing": null,
          "subscriber_count": 481,
          "modified_text": "286 days ago ",
          "is_modified": true,
          "groups": [],
          "in_group": false,
          "threat_hunter_scannable": false,
          "threat_hunter_has_agents": 1,
          "related_indicator_type": "IPv4",
          "related_indicator_is_active": 0,
          "targeted_technology": [],
          "organization": [],
          "targeted_botnet": [],
          "targeted_honeypot": [],
          "targeted_protocol": []
        },
        {
          "id": "6676e1f2035b0ede4dc2aa7b",
          "name": "ETIC Cybersecurity  2024-06-22  Port Scan",
          "description": "",
          "modified": "2024-06-22T14:50:23.117000",
          "created": "2024-06-22T14:38:42.165000",
          "tags": [],
          "references": [],
          "public": 1,
          "adversary": "",
          "targeted_countries": [],
          "malware_families": [],
          "attack_ids": [],
          "industries": [],
          "TLP": "white",
          "cloned_from": null,
          "export_count": 1,
          "upvotes_count": 0,
          "downvotes_count": 0,
          "votes_count": 0,
          "locked": false,
          "pulse_source": "api",
          "validator_count": 0,
          "comment_count": 0,
          "follower_count": 0,
          "vote": 0,
          "author": {
            "username": "EticCybersecurity",
            "id": "205841",
            "avatar_url": "/otxapi/users/avatar_image/media/avatars/user_205841/resized/80/avatar_3b9c358f36.png",
            "is_subscribed": false,
            "is_following": false
          },
          "indicator_type_counts": {},
          "indicator_count": 0,
          "is_author": false,
          "is_subscribing": null,
          "subscriber_count": 476,
          "modified_text": "287 days ago ",
          "is_modified": true,
          "groups": [],
          "in_group": false,
          "threat_hunter_scannable": false,
          "threat_hunter_has_agents": 1,
          "related_indicator_type": "IPv4",
          "related_indicator_is_active": 0,
          "targeted_technology": [],
          "organization": [],
          "targeted_botnet": [],
          "targeted_honeypot": [],
          "targeted_protocol": []
        },
        {
          "id": "667611079bdefb9507c2e2bb",
          "name": "Test1",
          "description": "",
          "modified": "2024-06-21T23:47:19.262000",
          "created": "2024-06-21T23:47:19.262000",
          "tags": [],
          "references": [],
          "public": 1,
          "adversary": "",
          "targeted_countries": [],
          "malware_families": [],
          "attack_ids": [],
          "industries": [],
          "TLP": "white",
          "cloned_from": "6675f7e775a670df0fc458e7",
          "export_count": 3,
          "upvotes_count": 0,
          "downvotes_count": 0,
          "votes_count": 0,
          "locked": false,
          "pulse_source": "web",
          "validator_count": 0,
          "comment_count": 0,
          "follower_count": 0,
          "vote": 0,
          "author": {
            "username": "gowrithehakcer",
            "id": "285688",
            "avatar_url": "https://otx.alienvault.com/assets/images/default-avatar.png",
            "is_subscribed": false,
            "is_following": false
          },
          "indicator_type_counts": {},
          "indicator_count": 0,
          "is_author": false,
          "is_subscribing": null,
          "subscriber_count": 0,
          "modified_text": "287 days ago ",
          "is_modified": false,
          "groups": [],
          "in_group": false,
          "threat_hunter_scannable": false,
          "threat_hunter_has_agents": 1,
          "related_indicator_type": "IPv4",
          "related_indicator_is_active": 0,
          "targeted_technology": [],
          "organization": [],
          "targeted_botnet": [],
          "targeted_honeypot": [],
          "targeted_protocol": []
        },
        {
          "id": "6674a6901437925ae80475fe",
          "name": "ETIC Cybersecurity  2024-06-21  Port Scan",
          "description": "",
          "modified": "2024-06-21T21:59:54.071000",
          "created": "2024-06-20T22:00:48.572000",
          "tags": [],
          "references": [],
          "public": 1,
          "adversary": "",
          "targeted_countries": [],
          "malware_families": [],
          "attack_ids": [],
          "industries": [],
          "TLP": "white",
          "cloned_from": null,
          "export_count": 6,
          "upvotes_count": 0,
          "downvotes_count": 0,
          "votes_count": 0,
          "locked": false,
          "pulse_source": "api",
          "validator_count": 0,
          "comment_count": 0,
          "follower_count": 0,
          "vote": 0,
          "author": {
            "username": "EticCybersecurity",
            "id": "205841",
            "avatar_url": "/otxapi/users/avatar_image/media/avatars/user_205841/resized/80/avatar_3b9c358f36.png",
            "is_subscribed": false,
            "is_following": false
          },
          "indicator_type_counts": {},
          "indicator_count": 0,
          "is_author": false,
          "is_subscribing": null,
          "subscriber_count": 483,
          "modified_text": "287 days ago ",
          "is_modified": true,
          "groups": [],
          "in_group": false,
          "threat_hunter_scannable": false,
          "threat_hunter_has_agents": 1,
          "related_indicator_type": "IPv4",
          "related_indicator_is_active": 0,
          "targeted_technology": [],
          "organization": [],
          "targeted_botnet": [],
          "targeted_honeypot": [],
          "targeted_protocol": []
        },
        {
          "id": "66735543e323d8575cb5cff1",
          "name": "ETIC Cybersecurity  2024-06-20  Port Scan",
          "description": "",
          "modified": "2024-06-20T21:59:45.093000",
          "created": "2024-06-19T22:01:39.958000",
          "tags": [],
          "references": [],
          "public": 1,
          "adversary": "",
          "targeted_countries": [],
          "malware_families": [],
          "attack_ids": [],
          "industries": [],
          "TLP": "white",
          "cloned_from": null,
          "export_count": 16,
          "upvotes_count": 0,
          "downvotes_count": 0,
          "votes_count": 0,
          "locked": false,
          "pulse_source": "api",
          "validator_count": 0,
          "comment_count": 0,
          "follower_count": 0,
          "vote": 0,
          "author": {
            "username": "EticCybersecurity",
            "id": "205841",
            "avatar_url": "/otxapi/users/avatar_image/media/avatars/user_205841/resized/80/avatar_3b9c358f36.png",
            "is_subscribed": false,
            "is_following": false
          },
          "indicator_type_counts": {},
          "indicator_count": 0,
          "is_author": false,
          "is_subscribing": null,
          "subscriber_count": 481,
          "modified_text": "288 days ago ",
          "is_modified": true,
          "groups": [],
          "in_group": false,
          "threat_hunter_scannable": false,
          "threat_hunter_has_agents": 1,
          "related_indicator_type": "IPv4",
          "related_indicator_is_active": 0,
          "targeted_technology": [],
          "organization": [],
          "targeted_botnet": [],
          "targeted_honeypot": [],
          "targeted_protocol": []
        },
        {
          "id": "667203693d1d5804a67fd7e1",
          "name": "ETIC Cybersecurity  2024-06-19  Port Scan",
          "description": "",
          "modified": "2024-06-19T22:00:04.200000",
          "created": "2024-06-18T22:00:09.746000",
          "tags": [],
          "references": [],
          "public": 1,
          "adversary": "",
          "targeted_countries": [],
          "malware_families": [],
          "attack_ids": [],
          "industries": [],
          "TLP": "white",
          "cloned_from": null,
          "export_count": 5,
          "upvotes_count": 0,
          "downvotes_count": 0,
          "votes_count": 0,
          "locked": false,
          "pulse_source": "api",
          "validator_count": 0,
          "comment_count": 0,
          "follower_count": 0,
          "vote": 0,
          "author": {
            "username": "EticCybersecurity",
            "id": "205841",
            "avatar_url": "/otxapi/users/avatar_image/media/avatars/user_205841/resized/80/avatar_3b9c358f36.png",
            "is_subscribed": false,
            "is_following": false
          },
          "indicator_type_counts": {},
          "indicator_count": 0,
          "is_author": false,
          "is_subscribing": null,
          "subscriber_count": 484,
          "modified_text": "289 days ago ",
          "is_modified": true,
          "groups": [],
          "in_group": false,
          "threat_hunter_scannable": false,
          "threat_hunter_has_agents": 1,
          "related_indicator_type": "IPv4",
          "related_indicator_is_active": 0,
          "targeted_technology": [],
          "organization": [],
          "targeted_botnet": [],
          "targeted_honeypot": [],
          "targeted_protocol": []
        },
        {
          "id": "6670b1ff6631421cb516e74b",
          "name": "ETIC Cybersecurity  2024-06-18  Port Scan",
          "description": "",
          "modified": "2024-06-18T21:59:48.125000",
          "created": "2024-06-17T22:00:31.275000",
          "tags": [],
          "references": [],
          "public": 1,
          "adversary": "",
          "targeted_countries": [],
          "malware_families": [],
          "attack_ids": [],
          "industries": [],
          "TLP": "white",
          "cloned_from": null,
          "export_count": 8,
          "upvotes_count": 0,
          "downvotes_count": 0,
          "votes_count": 0,
          "locked": false,
          "pulse_source": "api",
          "validator_count": 0,
          "comment_count": 0,
          "follower_count": 0,
          "vote": 0,
          "author": {
            "username": "EticCybersecurity",
            "id": "205841",
            "avatar_url": "/otxapi/users/avatar_image/media/avatars/user_205841/resized/80/avatar_3b9c358f36.png",
            "is_subscribed": false,
            "is_following": false
          },
          "indicator_type_counts": {},
          "indicator_count": 0,
          "is_author": false,
          "is_subscribing": null,
          "subscriber_count": 478,
          "modified_text": "290 days ago ",
          "is_modified": true,
          "groups": [],
          "in_group": false,
          "threat_hunter_scannable": false,
          "threat_hunter_has_agents": 1,
          "related_indicator_type": "IPv4",
          "related_indicator_is_active": 0,
          "targeted_technology": [],
          "organization": [],
          "targeted_botnet": [],
          "targeted_honeypot": [],
          "targeted_protocol": []
        },
        {
          "id": "666f607521b981837ef59103",
          "name": "ETIC Cybersecurity  2024-06-17  Port Scan",
          "description": "",
          "modified": "2024-06-17T22:00:00.016000",
          "created": "2024-06-16T22:00:21.832000",
          "tags": [],
          "references": [],
          "public": 1,
          "adversary": "",
          "targeted_countries": [],
          "malware_families": [],
          "attack_ids": [],
          "industries": [],
          "TLP": "white",
          "cloned_from": null,
          "export_count": 35,
          "upvotes_count": 0,
          "downvotes_count": 0,
          "votes_count": 0,
          "locked": false,
          "pulse_source": "api",
          "validator_count": 0,
          "comment_count": 0,
          "follower_count": 0,
          "vote": 0,
          "author": {
            "username": "EticCybersecurity",
            "id": "205841",
            "avatar_url": "/otxapi/users/avatar_image/media/avatars/user_205841/resized/80/avatar_3b9c358f36.png",
            "is_subscribed": false,
            "is_following": false
          },
          "indicator_type_counts": {},
          "indicator_count": 0,
          "is_author": false,
          "is_subscribing": null,
          "subscriber_count": 479,
          "modified_text": "291 days ago ",
          "is_modified": true,
          "groups": [],
          "in_group": false,
          "threat_hunter_scannable": false,
          "threat_hunter_has_agents": 1,
          "related_indicator_type": "IPv4",
          "related_indicator_is_active": 0,
          "targeted_technology": [],
          "organization": [],
          "targeted_botnet": [],
          "targeted_honeypot": [],
          "targeted_protocol": []
        },
        {
          "id": "666e0ef2e02e1f7426671dcc",
          "name": "ETIC Cybersecurity  2024-06-16  Port Scan",
          "description": "",
          "modified": "2024-06-16T22:00:01.918000",
          "created": "2024-06-15T22:00:18.309000",
          "tags": [],
          "references": [],
          "public": 1,
          "adversary": "",
          "targeted_countries": [],
          "malware_families": [],
          "attack_ids": [],
          "industries": [],
          "TLP": "white",
          "cloned_from": null,
          "export_count": 16,
          "upvotes_count": 0,
          "downvotes_count": 0,
          "votes_count": 0,
          "locked": false,
          "pulse_source": "api",
          "validator_count": 0,
          "comment_count": 0,
          "follower_count": 0,
          "vote": 0,
          "author": {
            "username": "EticCybersecurity",
            "id": "205841",
            "avatar_url": "/otxapi/users/avatar_image/media/avatars/user_205841/resized/80/avatar_3b9c358f36.png",
            "is_subscribed": false,
            "is_following": false
          },
          "indicator_type_counts": {},
          "indicator_count": 0,
          "is_author": false,
          "is_subscribing": null,
          "subscriber_count": 479,
          "modified_text": "292 days ago ",
          "is_modified": true,
          "groups": [],
          "in_group": false,
          "threat_hunter_scannable": false,
          "threat_hunter_has_agents": 1,
          "related_indicator_type": "IPv4",
          "related_indicator_is_active": 0,
          "targeted_technology": [],
          "organization": [],
          "targeted_botnet": [],
          "targeted_honeypot": [],
          "targeted_protocol": []
        },
        {
          "id": "665f8e68ba2c06b4302df9e9",
          "name": "ETIC Cybersecurity  2024-06-05  Port Scan",
          "description": "",
          "modified": "2024-06-05T21:59:56.271000",
          "created": "2024-06-04T22:00:08.555000",
          "tags": [],
          "references": [],
          "public": 1,
          "adversary": "",
          "targeted_countries": [],
          "malware_families": [],
          "attack_ids": [],
          "industries": [],
          "TLP": "white",
          "cloned_from": null,
          "export_count": 21,
          "upvotes_count": 0,
          "downvotes_count": 0,
          "votes_count": 0,
          "locked": false,
          "pulse_source": "api",
          "validator_count": 0,
          "comment_count": 0,
          "follower_count": 0,
          "vote": 0,
          "author": {
            "username": "EticCybersecurity",
            "id": "205841",
            "avatar_url": "/otxapi/users/avatar_image/media/avatars/user_205841/resized/80/avatar_3b9c358f36.png",
            "is_subscribed": false,
            "is_following": false
          },
          "indicator_type_counts": {},
          "indicator_count": 0,
          "is_author": false,
          "is_subscribing": null,
          "subscriber_count": 478,
          "modified_text": "303 days ago ",
          "is_modified": true,
          "groups": [],
          "in_group": false,
          "threat_hunter_scannable": false,
          "threat_hunter_has_agents": 1,
          "related_indicator_type": "IPv4",
          "related_indicator_is_active": 0,
          "targeted_technology": [],
          "organization": [],
          "targeted_botnet": [],
          "targeted_honeypot": [],
          "targeted_protocol": []
        },
        {
          "id": "660a6deab0fa7fb60b2873df",
          "name": "Firewall_Events_2024-01-20_12-31_AM",
          "description": "Firewall_Events_2024-01-20_12-31_AM\n\nInbound things Blocked",
          "modified": "2024-05-02T18:03:49.936000",
          "created": "2024-04-01T08:18:50.119000",
          "tags": [
            "Education",
            "Technology"
          ],
          "references": [
            "https://www.virustotal.com/gui/collection/0c9360cb9f8601bd6cdf912eb414d67902487f0c4eec96e952377e300ff4e983/iocs",
            "https://www.virustotal.com/graph/embed/gad6ea87df28241a198a6f64000309540dc730a3563f54a4899654f28c2e9cdff?theme=dark"
          ],
          "public": 1,
          "adversary": "",
          "targeted_countries": [
            "United States of America",
            "Canada"
          ],
          "malware_families": [],
          "attack_ids": [],
          "industries": [
            "Education",
            "Healthcare",
            "Government"
          ],
          "TLP": "white",
          "cloned_from": null,
          "export_count": 104,
          "upvotes_count": 0,
          "downvotes_count": 0,
          "votes_count": 0,
          "locked": false,
          "pulse_source": "web",
          "validator_count": 0,
          "comment_count": 0,
          "follower_count": 0,
          "vote": 0,
          "author": {
            "username": "Disable_Duck",
            "id": "244325",
            "avatar_url": "/otxapi/users/avatar_image/media/avatars/user_244325/resized/80/avatar_3b9c358f36.png",
            "is_subscribed": false,
            "is_following": false
          },
          "indicator_type_counts": {
            "hostname": 2,
            "FileHash-SHA256": 144,
            "URL": 3,
            "domain": 2
          },
          "indicator_count": 151,
          "is_author": false,
          "is_subscribing": null,
          "subscriber_count": 72,
          "modified_text": "338 days ago ",
          "is_modified": true,
          "groups": [],
          "in_group": false,
          "threat_hunter_scannable": true,
          "threat_hunter_has_agents": 1,
          "related_indicator_type": "IPv4",
          "related_indicator_is_active": 0,
          "targeted_technology": [],
          "organization": [],
          "targeted_botnet": [],
          "targeted_honeypot": [],
          "targeted_protocol": []
        },
        {
          "id": "65cd33874f16f9771c570300",
          "name": "Malicious IP's pulled from Modem logs - But wait, there's more, more more! Was able to pilfer a full Ave Maria RAT stack from ips",
          "description": "These are all ips pulled from my Modem that have hit as malicious either through criminalip.io or OTX. T. I was fortunate enough OTX was able to pull about 20 samples of .NET malware (showing as unclassified) and previously had not been in at least the public facing database. The stats are all over the plac; with some having samples as late as an hour ago. And some being last uploaded around 10-12 months ago. Compilation dates are around the same. This seems to be an active cluster emanating out of the CCP with one or two of the files looking like their some sort of Chinese browser modified for malicious purposes and actively communicating with a c2.",
          "modified": "2024-03-15T21:04:24.275000",
          "created": "2024-02-14T21:41:27.522000",
          "tags": [],
          "references": [],
          "public": 1,
          "adversary": "Unknown - Chinese Speaking",
          "targeted_countries": [
            "United States of America"
          ],
          "malware_families": [],
          "attack_ids": [],
          "industries": [
            "individuals"
          ],
          "TLP": "white",
          "cloned_from": null,
          "export_count": 9,
          "upvotes_count": 0,
          "downvotes_count": 0,
          "votes_count": 0,
          "locked": false,
          "pulse_source": "web",
          "validator_count": 0,
          "comment_count": 2,
          "follower_count": 0,
          "vote": 0,
          "author": {
            "username": "Merkd1904",
            "id": "196517",
            "avatar_url": "https://otx.alienvault.com/assets/images/default-avatar.png",
            "is_subscribed": false,
            "is_following": false
          },
          "indicator_type_counts": {
            "URL": 122,
            "domain": 49,
            "FileHash-SHA256": 20,
            "hostname": 19
          },
          "indicator_count": 210,
          "is_author": false,
          "is_subscribing": null,
          "subscriber_count": 64,
          "modified_text": "385 days ago ",
          "is_modified": true,
          "groups": [],
          "in_group": false,
          "threat_hunter_scannable": true,
          "threat_hunter_has_agents": 1,
          "related_indicator_type": "IPv4",
          "related_indicator_is_active": 0,
          "targeted_technology": [],
          "organization": [],
          "targeted_botnet": [],
          "targeted_honeypot": [],
          "targeted_protocol": []
        },
        {
          "id": "65c94533407798160221665d",
          "name": "Scan port 3389 RDP (S3#)",
          "description": "Scans hitting the server at TCP port 3389 RDP. Same IP should not appear more than once in 96 hours in our lists S3#.",
          "modified": "2024-03-12T22:03:29.700000",
          "created": "2024-02-11T22:07:46.299000",
          "tags": [
            "tcp",
            "RDP",
            "win",
            "windows",
            "admin",
            "honeypot",
            "Malicious IP",
            "botnet",
            "mirai",
            "blacklist",
            "scan"
          ],
          "references": [],
          "public": 1,
          "adversary": "",
          "targeted_countries": [],
          "malware_families": [],
          "attack_ids": [
            {
              "id": "T1595",
              "name": "",
              "display_name": ""
            }
          ],
          "industries": [],
          "TLP": "green",
          "cloned_from": null,
          "export_count": 11,
          "upvotes_count": 0,
          "downvotes_count": 0,
          "votes_count": 0,
          "locked": false,
          "pulse_source": "api",
          "validator_count": 0,
          "comment_count": 0,
          "follower_count": 0,
          "vote": 0,
          "author": {
            "username": "BotnetExposer",
            "id": "80256",
            "avatar_url": "/otxapi/users/avatar_image/media/avatars/user_80256/resized/80/avatar_f1760e796f.png",
            "is_subscribed": false,
            "is_following": false
          },
          "indicator_type_counts": {},
          "indicator_count": 0,
          "is_author": false,
          "is_subscribing": null,
          "subscriber_count": 2676,
          "modified_text": "388 days ago ",
          "is_modified": true,
          "groups": [],
          "in_group": false,
          "threat_hunter_scannable": false,
          "threat_hunter_has_agents": 1,
          "related_indicator_type": "IPv4",
          "related_indicator_is_active": 0,
          "targeted_technology": [
            "windows"
          ],
          "organization": [],
          "targeted_botnet": [
            "botnet",
            "mirai"
          ],
          "targeted_honeypot": [
            "honeypot"
          ],
          "targeted_protocol": [
            "tcp",
            "rdp"
          ]
        },
        {
          "id": "65bc16a14f54da75ddbd9e59",
          "name": "Scan port 3389 RDP (S3#)",
          "description": "Scans hitting the server at TCP port 3389 RDP. Same IP should not appear more than once in 96 hours in our lists S3#.",
          "modified": "2024-03-02T22:02:41.814000",
          "created": "2024-02-01T22:09:37.132000",
          "tags": [
            "tcp",
            "RDP",
            "win",
            "windows",
            "admin",
            "honeypot",
            "Malicious IP",
            "botnet",
            "mirai",
            "blacklist",
            "scan"
          ],
          "references": [],
          "public": 1,
          "adversary": "",
          "targeted_countries": [],
          "malware_families": [],
          "attack_ids": [
            {
              "id": "T1595",
              "name": "",
              "display_name": ""
            }
          ],
          "industries": [],
          "TLP": "green",
          "cloned_from": null,
          "export_count": 4,
          "upvotes_count": 0,
          "downvotes_count": 0,
          "votes_count": 0,
          "locked": false,
          "pulse_source": "api",
          "validator_count": 0,
          "comment_count": 0,
          "follower_count": 0,
          "vote": 0,
          "author": {
            "username": "BotnetExposer",
            "id": "80256",
            "avatar_url": "/otxapi/users/avatar_image/media/avatars/user_80256/resized/80/avatar_f1760e796f.png",
            "is_subscribed": false,
            "is_following": false
          },
          "indicator_type_counts": {},
          "indicator_count": 0,
          "is_author": false,
          "is_subscribing": null,
          "subscriber_count": 2676,
          "modified_text": "398 days ago ",
          "is_modified": true,
          "groups": [],
          "in_group": false,
          "threat_hunter_scannable": false,
          "threat_hunter_has_agents": 1,
          "related_indicator_type": "IPv4",
          "related_indicator_is_active": 0,
          "targeted_technology": [
            "windows"
          ],
          "organization": [],
          "targeted_botnet": [
            "botnet",
            "mirai"
          ],
          "targeted_honeypot": [
            "honeypot"
          ],
          "targeted_protocol": [
            "tcp",
            "rdp"
          ]
        },
        {
          "id": "65cbf48152a92fbb4d57deee",
          "name": "ETIC Cybersecurity  2024-02-14  Port Scan",
          "description": "",
          "modified": "2024-02-14T22:59:55.753000",
          "created": "2024-02-13T23:00:17.414000",
          "tags": [],
          "references": [],
          "public": 1,
          "adversary": "",
          "targeted_countries": [],
          "malware_families": [],
          "attack_ids": [],
          "industries": [],
          "TLP": "white",
          "cloned_from": null,
          "export_count": 4,
          "upvotes_count": 0,
          "downvotes_count": 0,
          "votes_count": 0,
          "locked": false,
          "pulse_source": "api",
          "validator_count": 0,
          "comment_count": 0,
          "follower_count": 0,
          "vote": 0,
          "author": {
            "username": "EticCybersecurity",
            "id": "205841",
            "avatar_url": "/otxapi/users/avatar_image/media/avatars/user_205841/resized/80/avatar_3b9c358f36.png",
            "is_subscribed": false,
            "is_following": false
          },
          "indicator_type_counts": {},
          "indicator_count": 0,
          "is_author": false,
          "is_subscribing": null,
          "subscriber_count": 484,
          "modified_text": "415 days ago ",
          "is_modified": true,
          "groups": [],
          "in_group": false,
          "threat_hunter_scannable": false,
          "threat_hunter_has_agents": 1,
          "related_indicator_type": "IPv4",
          "related_indicator_is_active": 0,
          "targeted_technology": [],
          "organization": [],
          "targeted_botnet": [],
          "targeted_honeypot": [],
          "targeted_protocol": []
        },
        {
          "id": "65caa2fa24878378746800c9",
          "name": "ETIC Cybersecurity  2024-02-13  Port Scan",
          "description": "",
          "modified": "2024-02-13T22:59:56.812000",
          "created": "2024-02-12T23:00:10.192000",
          "tags": [],
          "references": [],
          "public": 1,
          "adversary": "",
          "targeted_countries": [],
          "malware_families": [],
          "attack_ids": [],
          "industries": [],
          "TLP": "white",
          "cloned_from": null,
          "export_count": 11,
          "upvotes_count": 0,
          "downvotes_count": 0,
          "votes_count": 0,
          "locked": false,
          "pulse_source": "api",
          "validator_count": 0,
          "comment_count": 0,
          "follower_count": 0,
          "vote": 0,
          "author": {
            "username": "EticCybersecurity",
            "id": "205841",
            "avatar_url": "/otxapi/users/avatar_image/media/avatars/user_205841/resized/80/avatar_3b9c358f36.png",
            "is_subscribed": false,
            "is_following": false
          },
          "indicator_type_counts": {},
          "indicator_count": 0,
          "is_author": false,
          "is_subscribing": null,
          "subscriber_count": 480,
          "modified_text": "416 days ago ",
          "is_modified": true,
          "groups": [],
          "in_group": false,
          "threat_hunter_scannable": false,
          "threat_hunter_has_agents": 1,
          "related_indicator_type": "IPv4",
          "related_indicator_is_active": 0,
          "targeted_technology": [],
          "organization": [],
          "targeted_botnet": [],
          "targeted_honeypot": [],
          "targeted_protocol": []
        },
        {
          "id": "65c9517857237393fe6b9027",
          "name": "ETIC Cybersecurity  2024-02-12  Port Scan",
          "description": "",
          "modified": "2024-02-12T22:59:57.062000",
          "created": "2024-02-11T23:00:08.257000",
          "tags": [],
          "references": [],
          "public": 1,
          "adversary": "",
          "targeted_countries": [],
          "malware_families": [],
          "attack_ids": [],
          "industries": [],
          "TLP": "white",
          "cloned_from": null,
          "export_count": 14,
          "upvotes_count": 0,
          "downvotes_count": 0,
          "votes_count": 0,
          "locked": false,
          "pulse_source": "api",
          "validator_count": 0,
          "comment_count": 0,
          "follower_count": 0,
          "vote": 0,
          "author": {
            "username": "EticCybersecurity",
            "id": "205841",
            "avatar_url": "/otxapi/users/avatar_image/media/avatars/user_205841/resized/80/avatar_3b9c358f36.png",
            "is_subscribed": false,
            "is_following": false
          },
          "indicator_type_counts": {},
          "indicator_count": 0,
          "is_author": false,
          "is_subscribing": null,
          "subscriber_count": 479,
          "modified_text": "417 days ago ",
          "is_modified": true,
          "groups": [],
          "in_group": false,
          "threat_hunter_scannable": false,
          "threat_hunter_has_agents": 1,
          "related_indicator_type": "IPv4",
          "related_indicator_is_active": 0,
          "targeted_technology": [],
          "organization": [],
          "targeted_botnet": [],
          "targeted_honeypot": [],
          "targeted_protocol": []
        },
        {
          "id": "65c7fff37ab6c52762ba3bba",
          "name": "ETIC Cybersecurity  2024-02-11  Port Scan",
          "description": "",
          "modified": "2024-02-11T22:59:56.168000",
          "created": "2024-02-10T23:00:03.129000",
          "tags": [],
          "references": [],
          "public": 1,
          "adversary": "",
          "targeted_countries": [],
          "malware_families": [],
          "attack_ids": [],
          "industries": [],
          "TLP": "white",
          "cloned_from": null,
          "export_count": 13,
          "upvotes_count": 0,
          "downvotes_count": 0,
          "votes_count": 0,
          "locked": false,
          "pulse_source": "api",
          "validator_count": 0,
          "comment_count": 0,
          "follower_count": 0,
          "vote": 0,
          "author": {
            "username": "EticCybersecurity",
            "id": "205841",
            "avatar_url": "/otxapi/users/avatar_image/media/avatars/user_205841/resized/80/avatar_3b9c358f36.png",
            "is_subscribed": false,
            "is_following": false
          },
          "indicator_type_counts": {},
          "indicator_count": 0,
          "is_author": false,
          "is_subscribing": null,
          "subscriber_count": 477,
          "modified_text": "418 days ago ",
          "is_modified": true,
          "groups": [],
          "in_group": false,
          "threat_hunter_scannable": false,
          "threat_hunter_has_agents": 1,
          "related_indicator_type": "IPv4",
          "related_indicator_is_active": 0,
          "targeted_technology": [],
          "organization": [],
          "targeted_botnet": [],
          "targeted_honeypot": [],
          "targeted_protocol": []
        },
        {
          "id": "659dc44d79b18f82730ff8b6",
          "name": "Scan port 3389 RDP (S3#)",
          "description": "Scans hitting the server at TCP port 3389 RDP. Same IP should not appear more than once in 96 hours in our lists S3#.",
          "modified": "2024-02-08T22:04:20.002000",
          "created": "2024-01-09T22:10:21.469000",
          "tags": [
            "tcp",
            "RDP",
            "win",
            "windows",
            "admin",
            "honeypot",
            "Malicious IP",
            "botnet",
            "mirai",
            "blacklist",
            "scan"
          ],
          "references": [],
          "public": 1,
          "adversary": "",
          "targeted_countries": [],
          "malware_families": [],
          "attack_ids": [
            {
              "id": "T1595",
              "name": "",
              "display_name": ""
            }
          ],
          "industries": [],
          "TLP": "green",
          "cloned_from": null,
          "export_count": 10,
          "upvotes_count": 0,
          "downvotes_count": 0,
          "votes_count": 0,
          "locked": false,
          "pulse_source": "api",
          "validator_count": 0,
          "comment_count": 0,
          "follower_count": 0,
          "vote": 0,
          "author": {
            "username": "BotnetExposer",
            "id": "80256",
            "avatar_url": "/otxapi/users/avatar_image/media/avatars/user_80256/resized/80/avatar_f1760e796f.png",
            "is_subscribed": false,
            "is_following": false
          },
          "indicator_type_counts": {},
          "indicator_count": 0,
          "is_author": false,
          "is_subscribing": null,
          "subscriber_count": 2677,
          "modified_text": "421 days ago ",
          "is_modified": true,
          "groups": [],
          "in_group": false,
          "threat_hunter_scannable": false,
          "threat_hunter_has_agents": 1,
          "related_indicator_type": "IPv4",
          "related_indicator_is_active": 0,
          "targeted_technology": [
            "windows"
          ],
          "organization": [],
          "targeted_botnet": [
            "botnet",
            "mirai"
          ],
          "targeted_honeypot": [
            "honeypot"
          ],
          "targeted_protocol": [
            "tcp",
            "rdp"
          ]
        },
        {
          "id": "65972c5def5d7b88eda07650",
          "name": "Scan port 3389 RDP (S3#)",
          "description": "Scans hitting the server at TCP port 3389 RDP. Same IP should not appear more than once in 96 hours in our lists S3#.",
          "modified": "2024-02-03T22:04:12.031000",
          "created": "2024-01-04T22:08:29.751000",
          "tags": [
            "tcp",
            "RDP",
            "win",
            "windows",
            "admin",
            "honeypot",
            "Malicious IP",
            "botnet",
            "mirai",
            "blacklist",
            "scan"
          ],
          "references": [],
          "public": 1,
          "adversary": "",
          "targeted_countries": [],
          "malware_families": [],
          "attack_ids": [
            {
              "id": "T1595",
              "name": "",
              "display_name": ""
            }
          ],
          "industries": [],
          "TLP": "green",
          "cloned_from": null,
          "export_count": 16,
          "upvotes_count": 0,
          "downvotes_count": 0,
          "votes_count": 0,
          "locked": false,
          "pulse_source": "api",
          "validator_count": 0,
          "comment_count": 0,
          "follower_count": 0,
          "vote": 0,
          "author": {
            "username": "BotnetExposer",
            "id": "80256",
            "avatar_url": "/otxapi/users/avatar_image/media/avatars/user_80256/resized/80/avatar_f1760e796f.png",
            "is_subscribed": false,
            "is_following": false
          },
          "indicator_type_counts": {},
          "indicator_count": 0,
          "is_author": false,
          "is_subscribing": null,
          "subscriber_count": 2676,
          "modified_text": "426 days ago ",
          "is_modified": true,
          "groups": [],
          "in_group": false,
          "threat_hunter_scannable": false,
          "threat_hunter_has_agents": 1,
          "related_indicator_type": "IPv4",
          "related_indicator_is_active": 0,
          "targeted_technology": [
            "windows"
          ],
          "organization": [],
          "targeted_botnet": [
            "botnet",
            "mirai"
          ],
          "targeted_honeypot": [
            "honeypot"
          ],
          "targeted_protocol": [
            "tcp",
            "rdp"
          ]
        },
        {
          "id": "65bc228012a9fc5a5f95fcae",
          "name": "ETIC Cybersecurity  2024-02-02  Port Scan",
          "description": "",
          "modified": "2024-02-02T22:59:49.887000",
          "created": "2024-02-01T23:00:16.052000",
          "tags": [],
          "references": [],
          "public": 1,
          "adversary": "",
          "targeted_countries": [],
          "malware_families": [],
          "attack_ids": [],
          "industries": [],
          "TLP": "white",
          "cloned_from": null,
          "export_count": 7,
          "upvotes_count": 0,
          "downvotes_count": 0,
          "votes_count": 0,
          "locked": false,
          "pulse_source": "api",
          "validator_count": 0,
          "comment_count": 0,
          "follower_count": 0,
          "vote": 0,
          "author": {
            "username": "EticCybersecurity",
            "id": "205841",
            "avatar_url": "/otxapi/users/avatar_image/media/avatars/user_205841/resized/80/avatar_3b9c358f36.png",
            "is_subscribed": false,
            "is_following": false
          },
          "indicator_type_counts": {},
          "indicator_count": 0,
          "is_author": false,
          "is_subscribing": null,
          "subscriber_count": 480,
          "modified_text": "427 days ago ",
          "is_modified": true,
          "groups": [],
          "in_group": false,
          "threat_hunter_scannable": false,
          "threat_hunter_has_agents": 1,
          "related_indicator_type": "IPv4",
          "related_indicator_is_active": 0,
          "targeted_technology": [],
          "organization": [],
          "targeted_botnet": [],
          "targeted_honeypot": [],
          "targeted_protocol": []
        },
        {
          "id": "65bad0fde87a457c3041689e",
          "name": "ETIC Cybersecurity  2024-02-01  Port Scan",
          "description": "",
          "modified": "2024-02-01T22:59:56.188000",
          "created": "2024-01-31T23:00:13.877000",
          "tags": [],
          "references": [],
          "public": 1,
          "adversary": "",
          "targeted_countries": [],
          "malware_families": [],
          "attack_ids": [],
          "industries": [],
          "TLP": "white",
          "cloned_from": null,
          "export_count": 6,
          "upvotes_count": 0,
          "downvotes_count": 0,
          "votes_count": 0,
          "locked": false,
          "pulse_source": "api",
          "validator_count": 0,
          "comment_count": 0,
          "follower_count": 0,
          "vote": 0,
          "author": {
            "username": "EticCybersecurity",
            "id": "205841",
            "avatar_url": "/otxapi/users/avatar_image/media/avatars/user_205841/resized/80/avatar_3b9c358f36.png",
            "is_subscribed": false,
            "is_following": false
          },
          "indicator_type_counts": {},
          "indicator_count": 0,
          "is_author": false,
          "is_subscribing": null,
          "subscriber_count": 478,
          "modified_text": "428 days ago ",
          "is_modified": true,
          "groups": [],
          "in_group": false,
          "threat_hunter_scannable": false,
          "threat_hunter_has_agents": 1,
          "related_indicator_type": "IPv4",
          "related_indicator_is_active": 0,
          "targeted_technology": [],
          "organization": [],
          "targeted_botnet": [],
          "targeted_honeypot": [],
          "targeted_protocol": []
        },
        {
          "id": "65b82df26d9b88f9b218ef92",
          "name": "ETIC Cybersecurity  2024-01-30  Port Scan",
          "description": "",
          "modified": "2024-01-30T22:59:52.733000",
          "created": "2024-01-29T23:00:02.661000",
          "tags": [],
          "references": [],
          "public": 1,
          "adversary": "",
          "targeted_countries": [],
          "malware_families": [],
          "attack_ids": [],
          "industries": [],
          "TLP": "white",
          "cloned_from": null,
          "export_count": 5,
          "upvotes_count": 0,
          "downvotes_count": 0,
          "votes_count": 0,
          "locked": false,
          "pulse_source": "api",
          "validator_count": 0,
          "comment_count": 0,
          "follower_count": 0,
          "vote": 0,
          "author": {
            "username": "EticCybersecurity",
            "id": "205841",
            "avatar_url": "/otxapi/users/avatar_image/media/avatars/user_205841/resized/80/avatar_3b9c358f36.png",
            "is_subscribed": false,
            "is_following": false
          },
          "indicator_type_counts": {},
          "indicator_count": 0,
          "is_author": false,
          "is_subscribing": null,
          "subscriber_count": 477,
          "modified_text": "430 days ago ",
          "is_modified": true,
          "groups": [],
          "in_group": false,
          "threat_hunter_scannable": false,
          "threat_hunter_has_agents": 1,
          "related_indicator_type": "IPv4",
          "related_indicator_is_active": 0,
          "targeted_technology": [],
          "organization": [],
          "targeted_botnet": [],
          "targeted_honeypot": [],
          "targeted_protocol": []
        }
      ],
      "references": [
        "https://github.com/borestad/blocklist-abuseipdb/blob/main/abuseipdb-s100-3d.ipv4",
        "https://www.virustotal.com/gui/collection/0c9360cb9f8601bd6cdf912eb414d67902487f0c4eec96e952377e300ff4e983/iocs",
        "https://www.virustotal.com/gui/collection/789999053bd7022e2d79a887a5f959be573ce57d6c4f3165503438fbd5dd9ad5/graph",
        "https://www.virustotal.com/graph/embed/gad6ea87df28241a198a6f64000309540dc730a3563f54a4899654f28c2e9cdff?theme=dark"
      ],
      "related": {
        "alienvault": {
          "adversary": [],
          "malware_families": [],
          "industries": []
        },
        "other": {
          "adversary": [
            "Unknown - Chinese Speaking"
          ],
          "malware_families": [],
          "industries": [
            "Healthcare",
            "Education",
            "Individuals",
            "Government"
          ]
        }
      }
    },
    "false_positive": [],
    "validation": [],
    "asn": "AS57523 chang way technologies co. limited",
    "sections": [
      "general",
      "geo",
      "reputation",
      "url_list",
      "passive_dns",
      "malware",
      "nids_list",
      "http_scans"
    ]
  },
  "reputation": {
    "reputation": null
  },
  "geo": {
    "asn": "AS57523 chang way technologies co. limited"
  },
  "malware": {
    "data": [],
    "size": 0,
    "count": 0
  },
  "url_list": {
    "url_list": [
      {
        "url": "https://152.89.198.196",
        "date": "2023-08-02T22:08:28",
        "domain": "",
        "hostname": "152.89.198.196",
        "result": {
          "urlworker": {
            "http_code": 0
          },
          "safebrowsing": {
            "matches": []
          }
        },
        "httpcode": 0,
        "gsb": [],
        "encoded": "https%3A//152.89.198.196"
      },
      {
        "url": "http://152.89.198.196",
        "date": "2023-08-02T22:08:28",
        "domain": "",
        "hostname": "152.89.198.196",
        "result": {
          "urlworker": {
            "http_code": 0
          },
          "safebrowsing": {
            "matches": []
          }
        },
        "httpcode": 0,
        "gsb": [],
        "encoded": "http%3A//152.89.198.196"
      }
    ],
    "page_num": 1,
    "limit": 10,
    "paged": true,
    "has_next": false,
    "full_size": 2,
    "actual_size": 2
  },
  "passive_dns": {
    "passive_dns": [],
    "count": 0
  }
}